secondPlayer.v
module secondPlayer(clk, isGameOver, reset, actionEnable, action1, state1, action2, state2, health);
    input[2:0] action1, action2, state1;
    input clk, reset, actionEnable, isGameOver;
    output[1:0] health;
    reg[1:0] health = 2'b11;
    reg[1:0] wait_count = 2'b00;
    parameter player1S0 = 3'b100, player1S1 = 3'b010, player1S2 = 3'b001,
              player2S0 = 3'b001, player2S1 = 3'b010, player2S2 = 3'b100;  
    parameter kick = 3'b000,
              punch = 3'b001,
              await = 3'b010,
              jump = 3'b011,
              left1 = 3'b100,
              left2 = 3'b101,
              right1 = 3'b110,
              right2 = 3'b111;
    output [2:0] state2;          
    reg [2:0] state2 = player2S0;
    reg flagEnable = 2'b1;
    always @ (posedge clk or negedge reset or negedge actionEnable)
        if (reset == 0) begin
            state2 = player2S0;
            health = 2'b11;
            wait_count = 2'b00;
        end
        else if (flagEnable && actionEnable && ~isGameOver) begin
            case(state2)
                //001
                player2S0: begin
                    //plyer2 goes to 010
                    if (action2 == left1 || action2 == left2)
                        state2 = player2S1;
                        //health--
                        if(action1 == kick && state1 == player1S2)
                            health = health - 2'b01;
                    //waiting count
                    if (action2 == await) begin
                        wait_count = wait_count + 2'b01;
                        if (wait_count == 2'b10 && health != 2'b11) begin
                            health = health + 2'b01;
                            wait_count = 2'b00;
                        end
                        else if(wait_count == 2'b10)
                            wait_count = 2'b00;
                    end
                    else wait_count = 2'b00;
                    //else nothing to do, state2 doesn't change
                end
                //010
                player2S1: begin
                    //player2 goes to 100
                    if (action2 == left1 || action2 == left2) begin
                        state2 = player2S2;
                        //health -= 1
                        if ((action1 == kick) && (state1 == player1S1)) 
                            health = health - 2'b01;
                        //health -= 2
                        else if ((action1 == punch) && (state1 == player1S2)) 
                            health = health - 2'b10;
                    end
                    //player2 goes to 001
                    else if ((action2 == right1 || action2 == right2) || 
                            (action1 == kick && action2 == kick && state1 == player1S2))
                        state2 = player2S0;
                    //state2 doesn't change, health -= 1
                    else if((action2 == punch || action2 == await) && (action1 == kick) && (state1 == player1S2))
                        health = health - 2'b01;
                    //waiting count
                    if (action2 == await) begin
                        wait_count = wait_count + 2'b01;
                        if (wait_count == 2'b10 && health != 2'b11) begin
                            health = health + 2'b01;
                            wait_count = 2'b00;
                        end
                        else if(wait_count == 2'b10)
                            wait_count = 2'b00;
                    end
                    else wait_count = 2'b00;
                    //else nothing to do, state2 doesn't change
                end
                //100
                player2S2: begin
                    //player2 goes to 010
                    if ((action2 == right1 || action2 == right2) ||
                        (action1 == punch && action2 == punch && state1 == player1S2)||
                        (action1 == kick && action2 == kick && state1 != player1S0))
                            state2 = player2S1;
                            //health--
                            if((action2 == right1 || action2 == right2) && action1 == kick && state1 == player1S2)
                                health = health - 2'b01;
                    //health--, state2 doesn't change
                    else if(((action2 == await || action2 == left1 || action2 == left2 || action2 == punch)&&
                            action1 == kick && state1 == player1S1) ||
                            ((action2 == await || action2 == left1 || action2 == left2)&&
                        action1 == kick && state1 == player1S2))
                            health = health - 2'b01;
                    //health -= 2, state2 doesn't change
                    else if(((action2 == await || action2 == left1 || action2 == left2 || action2 == kick)&&
                        action1 == punch && state1 == player1S2))
                            health = health - 2'b10;
                            
                
                    //waiting count
                    if (action2 == await) begin
                        wait_count = wait_count + 2'b01;
                        if (wait_count == 2'b10 && health != 2'b11) begin
                            health = health + 2'b01;
                            wait_count = 2'b00;
                        end
                        else if(wait_count == 2'b10)
                            wait_count = 2'b00;
                    end
                    else wait_count = 2'b00;
                end
            endcase
            flagEnable = 1'b0;
        end
        else if (~actionEnable) 
            flagEnable = 1'b1;

endmodule

firstPlayer.v
module firstPlayer(clk, isGameOver, reset, actionEnable, action1, state1, action2, state2, health);
    input[2:0] action1, action2, state2;
    input clk, reset, actionEnable, isGameOver;
    output[1:0] health;
    reg[1:0] health = 2'b11;
    reg[1:0] wait_count = 2'b00;
    parameter player1S0 = 3'b100, player1S1 = 3'b010, player1S2 = 3'b001,
              player2S0 = 3'b001, player2S1 = 3'b010, player2S2 = 3'b100;  
    parameter kick = 3'b000,
              punch = 3'b001,
              await = 3'b010,
              jump = 3'b011,
              left1 = 3'b100,
              left2 = 3'b101,
              right1 = 3'b110,
              right2 = 3'b111;
    output [2:0] state1;          
    reg [2:0] state1 = player1S0;
    reg flagEnable = 2'b1;
    always @ (posedge clk or negedge reset or negedge actionEnable)
        if (reset == 0) begin
            state1 = player1S0;
            health = 2'b11;
            wait_count = 2'b00;
        end
        else if (actionEnable && flagEnable && ~isGameOver) begin
            case(state1)
                //100
                player1S0: begin
                    //plyer1 goes to 010
                    if (action1 == right1 || action1 == right2)
                        state1 = player1S1;
                        //health--
                        if(action2 == kick && state2 == player2S2)
                            health = health - 2'b01;
                    //waiting count
                    if (action1 == await) begin
                        wait_count = wait_count + 2'b01;
                        if (wait_count == 2'b10 && health != 2'b11) begin
                            health = health + 2'b01;
                            wait_count = 2'b00;
                        end
                        else if(wait_count == 2'b10)
                            wait_count = 2'b00;
                    end
                    else wait_count = 2'b00;
                    //else nothing to do, state1 doesn't change
                end
                //010
                player1S1: begin
                    //player1 goes to 001
                    if (action1 == right1 || action1 == right2) begin
                        state1 = player1S2;
                        //health -= 1
                        if ((action2 == kick) && (state2 == player2S1)) 
                            health = health - 2'b01;
                        //health -= 2
                        else if ((action2 == punch) && (state2 == player2S2)) 
                            health = health - 2'b10;
                    end
                    //player1 goes to 100
                    else if ((action1 == left1 || action1 == left2) || 
                            (action1 == kick && action2 == kick && state2 == player2S2))
                        state1 = player1S0;
                    //state1 doesn't change, health -= 1
                    else if((action1 == punch || action1 == await) && (action2 == kick) && (state2 == player2S2))
                        health = health - 2'b01;
                    //waiting count
                    if (action1 == await) begin
                        wait_count = wait_count + 2'b01;
                        if (wait_count == 2'b10 && health != 2'b11) begin
                            health = health + 2'b01;
                            wait_count = 2'b00;
                        end
                        else if(wait_count == 2'b10)
                            wait_count = 2'b00;
                    end
                    else wait_count = 2'b00;
                    //else nothing to do, state1 doesn't change
                end
                //001
                player1S2: begin
                    //player1 goes to 010
                    if ((action1 == left1 || action1 == left2) ||
                        (action1 == punch && action2 == punch && state2 == player2S2)||
                        (action1 == kick && action2 == kick && state2 != player2S0))
                            state1 = player1S1;
                            //health--
                            if((action1 == left1 || action1 == left2) && action2 == kick && state2 == player2S2)
                                health = health - 2'b01;
                    //health--, state1 doesn't change
                    else if(((action1 == await || action1 == right1 || action1 == right2 || action1 == punch)&&
                            action2 == kick && state2 == player2S1) ||
                            ((action1 == await || action1 == right1 || action1 == right2)&&
                        action2 == kick && state2 == player2S2))
                            health = health - 2'b01;
                    //health -= 2, state1 doesn't change
                    else if(((action1 == await || action1 == right1 || action1 == right2 || action1 == kick)&&
                        action2 == punch && state2 == player2S2))
                            health = health - 2'b10;
                            
                
                    //waiting count
                    if (action1 == await) begin
                        wait_count = wait_count + 2'b01;
                        if (wait_count == 2'b10 && health != 2'b11) begin
                            health = health + 2'b01;
                            wait_count = 2'b00;
                        end
                        else if(wait_count == 2'b10)
                            wait_count = 2'b00;
                    end
                    else wait_count = 2'b00;
                end
            endcase  
            flagEnable = 1'b0;
        end 
        else if (~actionEnable) 
            flagEnable = 1'b1;

endmodule

fightingGame.v
module fightingGame(health1, health2, firstWin, secondWin, state1,
    state2, clk, action1, action2, actionEnable, resetGame);
    output[1:0] health1;
    output[1:0] health2;
    output firstWin;
    output secondWin;
    output[2:0] state1;
    output[2:0] state2;
    input clk;
    input[2:0] action1;
    input[2:0] action2;
    input actionEnable;
    input resetGame;

    reg isGameOver = 1'b0;
    reg firstWin = 1'b0, secondWin = 1'b0;
    reg[2:0] currentState1 = 3'b100, currentState2 = 3'b001;
    firstPlayer p1(clk, isGameOver, resetGame, actionEnable, action1, state1, action2, currentState2, health1);
    secondPlayer p2(clk, isGameOver, resetGame, actionEnable, action1, currentState1, action2, state2, health2);

    always @ (negedge resetGame or negedge health1 or negedge health2 or posedge actionEnable)
        if (resetGame == 0) begin
            firstWin = 1'b0;
            secondWin = 1'b0;
            isGameOver = 1'b0;
            currentState1 = 3'b100;
            currentState2 = 3'b001;
        end
        else if(health1 == 0) begin
            secondWin = 1'b1;
            isGameOver = 1'b1;
        end
        else if(health2 == 0) begin
            firstWin = 1'b1;
            isGameOver = 1'b1;
        end
        else if (actionEnable) begin
            currentState1 = state1;
            currentState2 = state2;
        end
    

endmodule

testBench2.v
module testBench2;
    reg clk;
    reg[2:0] action1;
    reg[2:0] action2;
    reg actionEnable;
    reg resetGame;
    wire[1:0] health1;
    wire[1:0] health2;
    wire firstWin;
    wire secondWin;
    wire[2:0] state1;
    wire[2:0] state2;

    fightingGame fG(health1, health2, firstWin, secondWin, state1,
     state2, clk, action1, action2, actionEnable, resetGame);
    //clk
    initial
        begin
            $dumpfile("testBench2.vcd"); // Specify the VCD file name
            $dumpvars(0, testBench2); // Dump all variables at time 
            clk = 0;
            resetGame = 0;
            #5 resetGame = 1; 
            repeat (80)
            #5 clk = ~clk;
            $finish;
        end
    
    //start action      
    initial
        begin
            actionEnable = 0;
            #5
            action1 = 3'b100;
            action2 = 3'b110;
            actionEnable = 1;
            #20

            actionEnable = 0;
            #5
            action1 = 3'b110;
            action2 = 3'b100;
            actionEnable = 1;
            #20

            actionEnable = 0;
            #5
            action1 = 3'b000;
            action2 = 3'b100;
            actionEnable = 1;
            #20

            actionEnable = 0;
            #5
            action1 = 3'b010;
            action2 = 3'b100;
            actionEnable = 1;
            
            #20
            resetGame = 0;
            #30
            resetGame = 1;

            actionEnable = 0;
            #5
            action1 = 3'b110;
            action2 = 3'b100;
            actionEnable = 1;
            #20

            actionEnable = 0;
            #5
            action1 = 3'b110;
            action2 = 3'b010;
            actionEnable = 1;
            #20
            
            actionEnable = 0;
            #5
            action1 = 3'b110;
            action2 = 3'b010;
            actionEnable = 1;

            #20
            actionEnable = 0;
            #5 
            actionEnable = 1;
            

        end    
endmodule

testBench2.vcd
$date
	Sun Jan 28 17:10:44 2024
$end
$version
	Icarus Verilog
$end
$timescale
	1s
$end
$scope module testBench2 $end
$var wire 3 ! state2 [2:0] $end
$var wire 3 " state1 [2:0] $end
$var wire 1 # secondWin $end
$var wire 2 $ health2 [1:0] $end
$var wire 2 % health1 [1:0] $end
$var wire 1 & firstWin $end
$var reg 3 ' action1 [2:0] $end
$var reg 3 ( action2 [2:0] $end
$var reg 1 ) actionEnable $end
$var reg 1 * clk $end
$var reg 1 + resetGame $end
$scope module fG $end
$var wire 3 , action1 [2:0] $end
$var wire 3 - action2 [2:0] $end
$var wire 1 ) actionEnable $end
$var wire 1 * clk $end
$var wire 1 + resetGame $end
$var wire 3 . state2 [2:0] $end
$var wire 3 / state1 [2:0] $end
$var wire 2 0 health2 [1:0] $end
$var wire 2 1 health1 [1:0] $end
$var reg 3 2 currentState1 [2:0] $end
$var reg 3 3 currentState2 [2:0] $end
$var reg 1 & firstWin $end
$var reg 1 4 isGameOver $end
$var reg 1 # secondWin $end
$scope module p1 $end
$var wire 3 5 action1 [2:0] $end
$var wire 3 6 action2 [2:0] $end
$var wire 1 ) actionEnable $end
$var wire 1 * clk $end
$var wire 1 4 isGameOver $end
$var wire 1 + reset $end
$var wire 3 7 state2 [2:0] $end
$var parameter 3 8 await $end
$var parameter 3 9 jump $end
$var parameter 3 : kick $end
$var parameter 3 ; left1 $end
$var parameter 3 < left2 $end
$var parameter 3 = player1S0 $end
$var parameter 3 > player1S1 $end
$var parameter 3 ? player1S2 $end
$var parameter 3 @ player2S0 $end
$var parameter 3 A player2S1 $end
$var parameter 3 B player2S2 $end
$var parameter 3 C punch $end
$var parameter 3 D right1 $end
$var parameter 3 E right2 $end
$var reg 1 F flagEnable $end
$var reg 2 G health [1:0] $end
$var reg 3 H state1 [2:0] $end
$var reg 2 I wait_count [1:0] $end
$upscope $end
$scope module p2 $end
$var wire 3 J action1 [2:0] $end
$var wire 3 K action2 [2:0] $end
$var wire 1 ) actionEnable $end
$var wire 1 * clk $end
$var wire 1 4 isGameOver $end
$var wire 1 + reset $end
$var wire 3 L state1 [2:0] $end
$var parameter 3 M await $end
$var parameter 3 N jump $end
$var parameter 3 O kick $end
$var parameter 3 P left1 $end
$var parameter 3 Q left2 $end
$var parameter 3 R player1S0 $end
$var parameter 3 S player1S1 $end
$var parameter 3 T player1S2 $end
$var parameter 3 U player2S0 $end
$var parameter 3 V player2S1 $end
$var parameter 3 W player2S2 $end
$var parameter 3 X punch $end
$var parameter 3 Y right1 $end
$var parameter 3 Z right2 $end
$var reg 1 [ flagEnable $end
$var reg 2 \ health [1:0] $end
$var reg 3 ] state2 [2:0] $end
$var reg 2 ^ wait_count [1:0] $end
$upscope $end
$upscope $end
$upscope $end
$enddefinitions $end
$comment Show the parameter values. $end
$dumpall
b111 Z
b110 Y
b1 X
b100 W
b10 V
b1 U
b1 T
b10 S
b100 R
b101 Q
b100 P
b0 O
b11 N
b10 M
b111 E
b110 D
b1 C
b100 B
b10 A
b1 @
b1 ?
b10 >
b100 =
b101 <
b100 ;
b0 :
b11 9
b10 8
$end
#0
$dumpvars
b0 ^
b1 ]
b11 \
1[
b100 L
bx K
bx J
b0 I
b100 H
b11 G
1F
b1 7
bx 6
bx 5
04
b1 3
b100 2
b11 1
b11 0
b100 /
b1 .
bx -
bx ,
0+
0*
0)
bx (
bx '
0&
b11 %
b11 $
0#
b100 "
b1 !
$end
#5
1)
b110 (
b110 -
b110 6
b110 K
b100 '
b100 ,
b100 5
b100 J
1+
#10
0[
0F
1*
#15
0*
#20
1*
#25
1[
1F
0*
0)
#30
0F
b10 "
b10 /
b10 H
0[
b10 !
b10 .
b10 ]
1*
1)
b100 (
b100 -
b100 6
b100 K
b110 '
b110 ,
b110 5
b110 J
#35
0*
#40
1*
#45
0*
#50
1F
1[
1*
0)
#55
b10 3
b10 7
b10 2
b10 L
0*
1)
b0 '
b0 ,
b0 5
b0 J
#60
b100 3
b100 7
0[
b10 $
b10 0
b10 \
b100 !
b100 .
b100 ]
0F
1*
#65
0*
#70
1*
#75
1[
1F
0*
0)
#80
0F
b1 I
0[
1*
1)
b10 '
b10 ,
b10 5
b10 J
#85
0*
#90
1*
#95
0*
#100
b0 I
b100 "
b100 /
b100 H
b11 $
b11 0
b11 \
b1 !
b1 .
b1 ]
b1 3
b1 7
b100 2
b100 L
1*
0+
#105
0*
#110
1*
#115
0*
#120
1*
#125
0*
#130
1[
1F
1*
0)
1+
#135
0*
1)
b110 '
b110 ,
b110 5
b110 J
#140
0F
b10 "
b10 /
b10 H
0[
b10 !
b10 .
b10 ]
1*
#145
0*
#150
1*
#155
1F
1[
0*
0)
#160
0[
b1 ^
0F
b1 "
b1 /
b1 H
b10 3
b10 7
b10 2
b10 L
1*
1)
b10 (
b10 -
b10 6
b10 K
#165
0*
#170
1*
#175
0*
#180
1[
1F
1*
0)
#185
b1 2
b1 L
0*
1)
#190
0F
0[
b0 ^
1*
#195
0*
#200
1*
#205
1F
1[
0*
0)
#210
0[
b1 ^
0F
1*
1)
